sla_calculator/__init__.py
sla_calculator/calculator.py
sla_calculator-1.0.0.dist-info/WHEEL
sla_calculator-1.0.0.dist-info/METADATA
sla_calculator-1.0.0.dist-info/RECORD
