Metadata-Version: 2.1
Name: sla-calculator
Version: 1.0.0
Summary: A python module that will calculate the sla time based on working hours and holidays.
Home-page: https://github.com/swimlane/sla_calculator
Author: Michael Butler
Author-email: michael.butler@swimlane.com
Requires-Python: >=2.7, !=3.0.*, !=3.1.*, !=3.2.*, !=3.3.*, !=3.4.*, !=3.5.*
Classifier: Programming Language :: Python :: 2
Classifier: Programming Language :: Python :: 2.7
Classifier: Programming Language :: Python :: 3
Classifier: Programming Language :: Python :: 3.6
Classifier: Programming Language :: Python :: 3.7
Classifier: Programming Language :: Python :: 3.8
Classifier: Programming Language :: Python :: 3.9
Requires-Dist: holidays (==0.10.3)
Requires-Dist: pendulum (==2.1.2)
